pybd/__init__.py
pybd-0.1.2.dist-info/LICENSE
pybd-0.1.2.dist-info/METADATA
pybd-0.1.2.dist-info/WHEEL
pybd-0.1.2.dist-info/top_level.txt
pybd-0.1.2.dist-info/RECORD
