Metadata-Version: 2.1
Name: pybd
Version: 0.1.2
Summary: A Python API for accessing the Bazean database
Home-page: https://github.com/daytum/PyBD
Author: John T. Foster
Author-email: johntfoster@daytum.org
License: UNKNOWN
Platform: UNKNOWN
Classifier: Programming Language :: Python :: 3
Classifier: License :: OSI Approved :: Apache Software License
Classifier: Operating System :: OS Independent
Requires-Dist: numpy
Requires-Dist: psycopg2-binary
Requires-Dist: pandas
